odoo/addons/rma/README.rst
odoo/addons/rma/__init__.py
odoo/addons/rma/__manifest__.py
odoo/addons/rma/hooks.py
odoo/addons/rma/controllers/__init__.py
odoo/addons/rma/controllers/main.py
odoo/addons/rma/data/mail_data.xml
odoo/addons/rma/data/rma_operation_data.xml
odoo/addons/rma/data/stock_data.xml
odoo/addons/rma/i18n/es.po
odoo/addons/rma/i18n/nl.po
odoo/addons/rma/i18n/pt_BR.po
odoo/addons/rma/i18n/rma.pot
odoo/addons/rma/i18n/ro.po
odoo/addons/rma/i18n/zh_CN.po
odoo/addons/rma/migrations/13.0.1.0.0/post-migration.py
odoo/addons/rma/migrations/13.0.1.0.0/pre-migration.py
odoo/addons/rma/models/__init__.py
odoo/addons/rma/models/account_move.py
odoo/addons/rma/models/res_company.py
odoo/addons/rma/models/res_config_settings.py
odoo/addons/rma/models/res_partner.py
odoo/addons/rma/models/res_users.py
odoo/addons/rma/models/rma.py
odoo/addons/rma/models/rma_finalization.py
odoo/addons/rma/models/rma_operation.py
odoo/addons/rma/models/rma_tag.py
odoo/addons/rma/models/rma_team.py
odoo/addons/rma/models/stock_move.py
odoo/addons/rma/models/stock_picking.py
odoo/addons/rma/models/stock_warehouse.py
odoo/addons/rma/readme/CONFIGURE.rst
odoo/addons/rma/readme/CONTRIBUTORS.rst
odoo/addons/rma/readme/DESCRIPTION.rst
odoo/addons/rma/readme/ROADMAP.rst
odoo/addons/rma/readme/USAGE.rst
odoo/addons/rma/report/report.xml
odoo/addons/rma/security/ir.model.access.csv
odoo/addons/rma/security/rma_security.xml
odoo/addons/rma/static/description/icon.png
odoo/addons/rma/static/description/index.html
odoo/addons/rma/tests/__init__.py
odoo/addons/rma/tests/test_rma.py
odoo/addons/rma/views/menus.xml
odoo/addons/rma/views/report_rma.xml
odoo/addons/rma/views/res_config_settings_views.xml
odoo/addons/rma/views/res_partner_views.xml
odoo/addons/rma/views/rma_finalization_views.xml
odoo/addons/rma/views/rma_portal_templates.xml
odoo/addons/rma/views/rma_tag_views.xml
odoo/addons/rma/views/rma_team_views.xml
odoo/addons/rma/views/rma_views.xml
odoo13_addon_rma-13.0.2.7.4.dist-info/METADATA
odoo13_addon_rma-13.0.2.7.4.dist-info/WHEEL
odoo13_addon_rma-13.0.2.7.4.dist-info/top_level.txt
odoo13_addon_rma-13.0.2.7.4.dist-info/RECORD
